ai/__init__.py
ai/models.py
ai/prompts.py
ai/service.py
cli/__init__.py
cli/main.py
config/__init__.py
config/service.py
config/wizard.py
ticketplease/__init__.py
ticketplease/collector.py
ticketplease/generator.py
ticketplease/main.py
ticketplease/utils.py
ticketplease-0.1.1.dist-info/LICENSE
ticketplease-0.1.1.dist-info/METADATA
ticketplease-0.1.1.dist-info/WHEEL
ticketplease-0.1.1.dist-info/entry_points.txt
ticketplease-0.1.1.dist-info/RECORD
