Metadata-Version: 2.1
Name: ticketplease
Version: 0.1.1
Summary: CLI assistant for generating standardized task descriptions using AI
Home-page: https://github.com/kcmr/ticket-please
License: MIT
Keywords: cli,ai,jira,github,task-generation
Author: Kus Cámara
Author-email: kus.camara@gmail.com
Requires-Python: >=3.10,<4.0
Classifier: Development Status :: 3 - Alpha
Classifier: Intended Audience :: Developers
Classifier: License :: OSI Approved :: MIT License
Classifier: Programming Language :: Python :: 3
Classifier: Programming Language :: Python :: 3.10
Classifier: Programming Language :: Python :: 3.11
Classifier: Programming Language :: Python :: 3.12
Classifier: Programming Language :: Python :: 3.13
Classifier: Topic :: Software Development :: Libraries :: Python Modules
Classifier: Topic :: Utilities
Requires-Dist: keyring (>=24.0.0,<25.0.0)
Requires-Dist: litellm (>=1.0.0,<2.0.0)
Requires-Dist: pyperclip (>=1.8.0,<2.0.0)
Requires-Dist: questionary (>=2.0.0,<3.0.0)
Requires-Dist: rich (>=13.0.0,<14.0.0)
Requires-Dist: toml (>=0.10.0,<0.11.0)
Requires-Dist: typer (>=0.12.0)
Project-URL: Repository, https://github.com/kcmr/ticket-please
